pygdsm/__init__.py
pygdsm/base_observer.py
pygdsm/base_skymodel.py
pygdsm/component_data.py
pygdsm/gsm08.py
pygdsm/gsm16.py
pygdsm/haslam.py
pygdsm/lfsm.py
pygdsm/plot_utils.py
pygdsm-1.5.0.dist-info/LICENSE
pygdsm-1.5.0.dist-info/METADATA
pygdsm-1.5.0.dist-info/WHEEL
pygdsm-1.5.0.dist-info/top_level.txt
pygdsm-1.5.0.dist-info/RECORD
