Metadata-Version: 2.1
Name: pygdsm
Version: 1.5.0
Summary: Python Global Sky Model of diffuse Galactic radio emission
Home-page: https://github.com/telegraphic/pygdsm
Author: Danny Price
Author-email: dancpr@berkeley.edu
License: MIT
Keywords: radio astronomy sky model galactic diffuse emission
Classifier: Development Status :: 5 - Production/Stable
Classifier: Intended Audience :: Science/Research
Classifier: Topic :: Scientific/Engineering :: Astronomy
Classifier: License :: OSI Approved :: MIT License
Classifier: Programming Language :: Python :: 3
Classifier: Programming Language :: Python :: 3.6
Classifier: Programming Language :: Python :: 3.7
Classifier: Programming Language :: Python :: 3.8
Classifier: Programming Language :: Python :: 3.9
Classifier: Programming Language :: Python :: 3.10
Classifier: Programming Language :: Python :: 3.11
License-File: LICENSE
Requires-Dist: numpy
Requires-Dist: scipy
Requires-Dist: astropy
Requires-Dist: h5py
Requires-Dist: healpy
Requires-Dist: matplotlib
Requires-Dist: pyephem
Requires-Dist: pytest
